{"v":1,"lamport":1,"ops":[{"kind":"create_task","nonce":"5290f4d541c7afe1efc6939e65f8fbb8","title":"Cache heal mutex can block auth_status past its bound","description":"healingWrapper.heal (internal/cache/cache.go:203) holds a non-ctx-aware sync.Mutex across the helper subprocess; a heal running concurrently with a status read can block Get/Degraded past authStatusTimeout (context.WithTimeout cannot interrupt a mutex Lock). Needs cache/heal locking restructure (e.g. TryLock + locked-note fallback, or ctx-aware semaphore). Found during the v0.10.3 auth_status fix; not the observed incident (that fired on every doctor run; this needs a coincident slow heal while degraded+locked).","type":"task","priority":2,"branch":"","parent":"","labels":null},{"kind":"add_criterion","id":"d180e6cab610161f10432a9e83b97464","text":"auth_status returns within authStatusTimeout even while a heal is mid-flight (test with a slow fake helper)","script":""},{"kind":"add_criterion","id":"e4aea0e7875e584cd1a60fbda48d24f4","text":"no consent-path behavior change","script":""}]}